geokey_webresources
travis_ci
