Metadata-Version: 1.1
Name: geokey-webresources
Version: 0.2.3
Summary: Add web resources to GeoKey projects
Home-page: https://github.com/ExCiteS/geokey-webresources
Author: ExCiteS
Author-email: excites@ucl.ac.uk
License: MIT
Download-URL: https://github.com/ExCiteS/geokey-webresources/tarball/0.2.3
Platform: UNKNOWN
